nameko_injector/__init__.py
nameko_injector/core.py
nameko_injector/testing/__init__.py
nameko_injector/testing/pytest_fixtures.py
tests/__init__.py
tests/conftest.py
tests/dummy_service.py
tests/test_http.py
tests/test_injected.py
tests/test_readme_example.py
tests/test_request_scope.py
tests/test_rpc.py
tests/test_teardown_in_scopes.py
tests/test_with_worker_context.py
nameko_injector-1.1.2.dist-info/METADATA
nameko_injector-1.1.2.dist-info/WHEEL
nameko_injector-1.1.2.dist-info/top_level.txt
nameko_injector-1.1.2.dist-info/RECORD
