Metadata-Version: 2.1
Name: nameko-injector
Version: 1.1.2
Summary: Injector support in nameko
Home-page: https://github.com/signalpillar/nameko-injector
Author: Volodymyr Vitvitskyi
Author-email: UNKNOWN
License: MIT
Platform: linux
Platform: osx
Classifier: Development Status :: 4 - Beta
Classifier: Intended Audience :: Developers
Classifier: License :: OSI Approved :: MIT License
Classifier: Operating System :: POSIX
Classifier: Operating System :: Microsoft :: Windows
Classifier: Operating System :: MacOS :: MacOS X
Classifier: Topic :: Software Development :: Testing
Classifier: Topic :: Software Development :: Libraries
Classifier: Topic :: Utilities
Classifier: Programming Language :: Python
Requires-Dist: nameko (>=2.0.0)
Requires-Dist: injector (>=0.18.0)
